lsmmdma/__init__.py
lsmmdma/initializers.py
lsmmdma/main.py
lsmmdma/metrics.py
lsmmdma/mmdma_functions.py
lsmmdma/mmdma_functions_bis.py
lsmmdma/train.py
lsmmdma/train_bis.py
lsmmdma/version.py
lsmmdma/data/__init__.py
lsmmdma/data/checkpointer.py
lsmmdma/data/data_pipeline.py
lsmtest10-0.0.1.dist-info/LICENSE
lsmtest10-0.0.1.dist-info/METADATA
lsmtest10-0.0.1.dist-info/WHEEL
lsmtest10-0.0.1.dist-info/top_level.txt
lsmtest10-0.0.1.dist-info/RECORD
