Metadata-Version: 2.1
Name: lsmtest10
Version: 0.0.1
Summary: Scaling MMD-MA.
Home-page: https://github.com/google-research/large_scale_mmdma
Author: Google LLC
Author-email: lpapaxanthos@google.com
License: Apache 2.0
Keywords: kernel,data integration
Platform: UNKNOWN
Classifier: Intended Audience :: Science/Research
Classifier: Topic :: Scientific/Engineering :: Artificial Intelligence
Classifier: Programming Language :: Python :: 3
Classifier: License :: OSI Approved :: Apache Software License
License-File: LICENSE
Requires-Dist: absl-py
Requires-Dist: numpy (>=1.19)
Requires-Dist: torch (>=1.10)
Requires-Dist: tensorflow-cpu (>=2.7)
Requires-Dist: pykeops (==1.5)
Requires-Dist: typing (==3.7.4.3)
Requires-Dist: dataclasses (==0.6)
Requires-Dist: cmake (==3.18)
Requires-Dist: setuptools (>=59.5.0)
Requires-Dist: tenacity (>=8.0)
Requires-Dist: sklearn
